{
  "latest": {
    "version": "0.3.3",
    "releaseDate": "2026-05-14T19:42:35.305Z",
    "notes": "- fix(setup): notebooklm 安裝改用 'uv tool install --force'，避免上次中斷殘留的 notebooklm-mcp 執行檔讓 install 卡住\n- fix(e2e): notebooklm spec 修對 locator（之前用 '尚未安裝' 但 UI 是 '未安裝'，整支 spec vacuously pass 沒實際測試）；新增 idempotency 驗證\n- fix(e2e): telegram pair spec 主動 ack 上一次 deploy 的 執行中 row 才按新增部署（WHMCS 不允許併行 deploy，且 ack 不跨 Playwright session）",
    "artifacts": [
      {
        "platform": "linux",
        "arch": "x64",
        "url": "https://github.com/YJ-Software/mission-control-center/releases/download/v0.3.3/mission-control-v0.3.3-linux-x64.tar.gz",
        "sha256": "d24a4a4ff4fa400b0df0db6253e588dae4f8c07c2b4a26ac0821fd3a4cc4c0a6",
        "size": 18435302
      }
    ]
  },
  "history": [
    {
      "version": "0.3.2",
      "releaseDate": "2026-05-14T05:35:53.274Z"
    },
    {
      "version": "0.3.1",
      "releaseDate": "2026-05-12T07:55:50.251Z"
    },
    {
      "version": "0.3.0",
      "releaseDate": "2026-05-12T07:20:01.368Z"
    },
    {
      "version": "0.2.9",
      "releaseDate": "2026-05-12T07:15:02.330Z"
    },
    {
      "version": "0.2.8",
      "releaseDate": "2026-05-12T02:29:25.395Z"
    },
    {
      "version": "0.2.7",
      "releaseDate": "2026-05-11T17:12:14.581Z"
    },
    {
      "version": "0.2.6",
      "releaseDate": "2026-05-11T09:42:59.808Z"
    },
    {
      "version": "0.2.5",
      "releaseDate": "2026-05-08T06:21:23.749Z"
    },
    {
      "version": "0.2.4",
      "releaseDate": "2026-05-06T17:42:28.640Z"
    },
    {
      "version": "0.2.3",
      "releaseDate": "2026-05-06T17:09:32.804Z"
    }
  ]
}
